odoo9_addon_web_editor_background_color-9.0.1.0.0-py2.7-nspkg.pth
odoo9_addon_web_editor_background_color-9.0.1.0.0.dist-info/top_level.txt
odoo9_addon_web_editor_background_color-9.0.1.0.0.dist-info/WHEEL
odoo9_addon_web_editor_background_color-9.0.1.0.0.dist-info/RECORD
odoo9_addon_web_editor_background_color-9.0.1.0.0.dist-info/metadata.json
odoo9_addon_web_editor_background_color-9.0.1.0.0.dist-info/DESCRIPTION.rst
odoo9_addon_web_editor_background_color-9.0.1.0.0.dist-info/METADATA
odoo9_addon_web_editor_background_color-9.0.1.0.0.dist-info/namespace_packages.txt
odoo_addons/web_editor_background_color/__openerp__.py
odoo_addons/web_editor_background_color/__init__.py
odoo_addons/web_editor_background_color/README.rst
odoo_addons/web_editor_background_color/i18n/es.po
odoo_addons/web_editor_background_color/i18n/sl.po
odoo_addons/web_editor_background_color/i18n/fr.po
odoo_addons/web_editor_background_color/views/snippets.xml
odoo_addons/web_editor_background_color/views/assets.xml
odoo_addons/web_editor_background_color/static/description/mass_mailing_editor.png
odoo_addons/web_editor_background_color/static/description/icon.png
odoo_addons/web_editor_background_color/static/src/js/background_color.js
odoo_addons/web_editor_background_color/static/src/css/background_color.less
odoo_addons/web_editor_background_color/static/src/xml/colorpicker.xml
odoo_addons/web_editor_background_color/static/src/lib/bootstrap-colorpicker/alpha-horizontal.png
odoo_addons/web_editor_background_color/static/src/lib/bootstrap-colorpicker/colorpicker.less
odoo_addons/web_editor_background_color/static/src/lib/bootstrap-colorpicker/bootstrap-colorpicker.js
odoo_addons/web_editor_background_color/static/src/lib/bootstrap-colorpicker/hue.png
odoo_addons/web_editor_background_color/static/src/lib/bootstrap-colorpicker/alpha.png
odoo_addons/web_editor_background_color/static/src/lib/bootstrap-colorpicker/hue-horizontal.png
odoo_addons/web_editor_background_color/static/src/lib/bootstrap-colorpicker/saturation.png
